Metadata-Version: 2.1
Name: cgpacalculatorpsg
Version: 0.0.1
Summary: A Package used for calculating GPA CGPA By Arjun K PSG ICE
Home-page: UNKNOWN
Author: Arjun K
Author-email: arjunkrishnarajv@gmail.com
License: MIT
Keywords: cgpacalculatorpsg
Platform: UNKNOWN
Classifier: Development Status :: 5 - Production/Stable
Classifier: Intended Audience :: Education
Classifier: Operating System :: Microsoft :: Windows :: Windows 10
Classifier: License :: OSI Approved :: MIT License
Classifier: Programming Language :: Python :: 3
License-File: LICENSE.txt
